aidetector/__init__.py
aidetector/aidetectorclass.py
aidetector/command_interface.py
aidetector/inference.py
aidetector/tokenization.py
aidetector/training.py
aidetector-0.0.2.dist-info/LICENSE
aidetector-0.0.2.dist-info/METADATA
aidetector-0.0.2.dist-info/WHEEL
aidetector-0.0.2.dist-info/entry_points.txt
aidetector-0.0.2.dist-info/top_level.txt
aidetector-0.0.2.dist-info/RECORD
