Metadata-Version: 2.1
Name: aidetector
Version: 0.0.2
Summary: AiDetector provides a simple interface to train and run models to classify if text was generated by AI or not.
Home-page: https://github.com/baileytec-labs
Author: Sean Bailey
Author-email: seanbailey518@gmail.com
Classifier: Programming Language :: Python :: 3
Classifier: License :: OSI Approved :: Apache Software License
Classifier: Operating System :: OS Independent
Requires-Python: >=3.9
License-File: LICENSE
Requires-Dist: spacy
Requires-Dist: torch
Requires-Dist: torchtext
Requires-Dist: halo
Requires-Dist: pandas
Requires-Dist: scikit-learn
